datasupplement/__init__.py
datasupplement/parser.py
datasupplement-0.0.1.dist-info/licenses/LICENSE
datasupplement-0.0.1.dist-info/METADATA
datasupplement-0.0.1.dist-info/WHEEL
datasupplement-0.0.1.dist-info/top_level.txt
datasupplement-0.0.1.dist-info/RECORD
